MANIFEST.in
README.rst
setup.py
aliyun_python_sdk_yundun_test.egg-info/PKG-INFO
aliyun_python_sdk_yundun_test.egg-info/SOURCES.txt
aliyun_python_sdk_yundun_test.egg-info/dependency_links.txt
aliyun_python_sdk_yundun_test.egg-info/requires.txt
aliyun_python_sdk_yundun_test.egg-info/top_level.txt
aliyunsdkyundun/__init__.py
aliyunsdkyundun/request/__init__.py
aliyunsdkyundun/request/v20150227/AllMalwareNumRequest.py
aliyunsdkyundun/request/v20150227/CurrentDdosAttackNumRequest.py
aliyunsdkyundun/request/v20150227/TodayAegisOnlineRateRequest.py
aliyunsdkyundun/request/v20150227/TodayAllkbpsRequest.py
aliyunsdkyundun/request/v20150227/TodayAllppsRequest.py
aliyunsdkyundun/request/v20150227/TodayBackdoorRequest.py
aliyunsdkyundun/request/v20150227/TodayCrackInterceptRequest.py
aliyunsdkyundun/request/v20150227/TodayMalwareNumRequest.py
aliyunsdkyundun/request/v20150227/TodayqpsByRegionRequest.py
aliyunsdkyundun/request/v20150227/WebAttackNumRequest.py
aliyunsdkyundun/request/v20150227/__init__.py
aliyunsdkyundun/request/v20150416/AddCNameWafRequest.py
aliyunsdkyundun/request/v20150416/BruteforceLogRequest.py
aliyunsdkyundun/request/v20150416/CloseCCProtectRequest.py
aliyunsdkyundun/request/v20150416/ClosePortScanRequest.py
aliyunsdkyundun/request/v20150416/CloseVulScanRequest.py
aliyunsdkyundun/request/v20150416/ConfigDdosRequest.py
aliyunsdkyundun/request/v20150416/ConfirmLoginRequest.py
aliyunsdkyundun/request/v20150416/DdosFlowGraphRequest.py
aliyunsdkyundun/request/v20150416/DdosLogRequest.py
aliyunsdkyundun/request/v20150416/DeleteBackDoorFileRequest.py
aliyunsdkyundun/request/v20150416/DeleteCNameWafRequest.py
aliyunsdkyundun/request/v20150416/DetectVulByIdRequest.py
aliyunsdkyundun/request/v20150416/DetectVulByIpRequest.py
aliyunsdkyundun/request/v20150416/GetDdosConfigOptionsRequest.py
aliyunsdkyundun/request/v20150416/ListInstanceInfosRequest.py
aliyunsdkyundun/request/v20150416/LogineventLogRequest.py
aliyunsdkyundun/request/v20150416/OpenCCProtectRequest.py
aliyunsdkyundun/request/v20150416/OpenPortScanRequest.py
aliyunsdkyundun/request/v20150416/OpenVulScanRequest.py
aliyunsdkyundun/request/v20150416/QueryDdosConfigRequest.py
aliyunsdkyundun/request/v20150416/SecureCheckRequest.py
